pypelearn/AngelEncoder.py
pypelearn/AngelEncoderRun.py
pypelearn/GUI.py
pypelearn/__init__.py
pypelearn/models.py
pypelearn-0.0.20.dist-info/METADATA
pypelearn-0.0.20.dist-info/RECORD
pypelearn-0.0.20.dist-info/WHEEL
pypelearn-0.0.20.dist-info/top_level.txt
