Metadata-Version: 2.1
Name: pypelearn
Version: 0.0.20
Summary: A pipeline library for testing and validating time series data
Home-page: https://github.com/alexharston/pypelearn
Author: Alex Harston
Author-email: alex@harston.io
License: MIT
Keywords: pypelearn machine learning time series pipeline
Platform: UNKNOWN
Classifier: Development Status :: 4 - Beta
Classifier: Programming Language :: Python :: 3
Classifier: License :: OSI Approved :: MIT License
Classifier: Operating System :: OS Independent
Requires-Python: >=3
Requires-Dist: statsmodels
Requires-Dist: argparse
Requires-Dist: pandas
Requires-Dist: matplotlib
Requires-Dist: numpy
Requires-Dist: scipy
Requires-Dist: sklearn
Requires-Dist: tensorflow
